lpcML/__init__.py
lpcML/data_processing.py
lpcML/model.py
lpcML/model_fitting.py
lpcML/plot.py
lpcML/simulation_data_extractor.py
lpcml-0.1.2.dist-info/licenses/LICENSE
lpcml-0.1.2.dist-info/METADATA
lpcml-0.1.2.dist-info/WHEEL
lpcml-0.1.2.dist-info/top_level.txt
lpcml-0.1.2.dist-info/RECORD
