Metadata-Version: 2.4
Name: lpcML
Version: 0.1.2
Summary: LPC ML is a machine learning workflow developed to optimize and analyze the impact of different design parameters on laser power converters (LPCs) solar cells
Home-page: https://gitlab.citius.usc.es/julian.garcia.fernandez/lpcML
Author: Julian Garcia Fernandez 
Author-email: julian.garcia.fernandez2@usc.es
Classifier: Topic :: Utilities
Classifier: Intended Audience :: Developers
Classifier: Intended Audience :: Information Technology
Classifier: License :: OSI Approved :: GNU General Public License v3 (GPLv3)
Classifier: Operating System :: Unix
Classifier: Programming Language :: Python :: 3
Requires-Python: >=3.6
License-File: LICENSE
Requires-Dist: torch
Requires-Dist: pytorch_lightning
Requires-Dist: wandb
Requires-Dist: numpy
Requires-Dist: pandas
Requires-Dist: scikit-learn
Requires-Dist: torcheval
Requires-Dist: pathlib
Dynamic: author
Dynamic: author-email
Dynamic: classifier
Dynamic: description
Dynamic: description-content-type
Dynamic: home-page
Dynamic: license-file
Dynamic: requires-dist
Dynamic: requires-python
Dynamic: summary
